ansys/hps/client/__init__.py
ansys/hps/client/__version__.py
ansys/hps/client/authenticate.py
ansys/hps/client/check_version.py
ansys/hps/client/client.py
ansys/hps/client/connection.py
ansys/hps/client/exceptions.py
ansys/hps/client/warnings.py
ansys/hps/client/auth/__init__.py
ansys/hps/client/auth/api/__init__.py
ansys/hps/client/auth/api/auth_api.py
ansys/hps/client/auth/resource/__init__.py
ansys/hps/client/auth/resource/user.py
ansys/hps/client/auth/schema/__init__.py
ansys/hps/client/auth/schema/user.py
ansys/hps/client/common/__init__.py
ansys/hps/client/common/base_resource.py
ansys/hps/client/common/base_schema.py
ansys/hps/client/common/dict_model.py
ansys/hps/client/common/restricted_value.py
ansys/hps/client/jms/__init__.py
ansys/hps/client/jms/keys.py
ansys/hps/client/jms/api/__init__.py
ansys/hps/client/jms/api/base.py
ansys/hps/client/jms/api/jms_api.py
ansys/hps/client/jms/api/project_api.py
ansys/hps/client/jms/resource/.gitignore
ansys/hps/client/jms/resource/__init__.py
ansys/hps/client/jms/resource/algorithm.py
ansys/hps/client/jms/resource/file.py
ansys/hps/client/jms/resource/fitness_definition.py
ansys/hps/client/jms/resource/job.py
ansys/hps/client/jms/resource/job_definition.py
ansys/hps/client/jms/resource/license_context.py
ansys/hps/client/jms/resource/operation.py
ansys/hps/client/jms/resource/parameter_definition.py
ansys/hps/client/jms/resource/parameter_mapping.py
ansys/hps/client/jms/resource/permission.py
ansys/hps/client/jms/resource/project.py
ansys/hps/client/jms/resource/selection.py
ansys/hps/client/jms/resource/task.py
ansys/hps/client/jms/resource/task_command.py
ansys/hps/client/jms/resource/task_command_definition.py
ansys/hps/client/jms/resource/task_definition.py
ansys/hps/client/jms/resource/task_definition_template.py
ansys/hps/client/jms/schema/__init__.py
ansys/hps/client/jms/schema/algorithm.py
ansys/hps/client/jms/schema/file.py
ansys/hps/client/jms/schema/fitness_definition.py
ansys/hps/client/jms/schema/job.py
ansys_hps_client-0.11.1.dist-info/licenses/LICENSE
ansys_hps_client-0.11.1.dist-info/WHEEL
ansys_hps_client-0.11.1.dist-info/METADATA
ansys_hps_client-0.11.1.dist-info/RECORD
