Metadata-Version: 2.4
Name: ansys-hps-client
Version: 0.11.1
Summary: A python client for Ansys HPC Platform Services
Author-email: "ANSYS, Inc." <pyansys.core@ansys.com>
Maintainer-email: "ANSYS, Inc." <pyansys.core@ansys.com>
Requires-Python: >=3.10,<4.0
Classifier: Development Status :: 4 - Beta
Classifier: Intended Audience :: Science/Research
Classifier: Topic :: Scientific/Engineering :: Information Analysis
Classifier: Programming Language :: Python :: 3.10
Classifier: Programming Language :: Python :: 3.11
Classifier: Programming Language :: Python :: 3.12
Classifier: Programming Language :: Python :: 3.13
Classifier: License :: OSI Approved :: MIT License
Classifier: Operating System :: OS Independent
License-File: LICENSE
Requires-Dist: requests>=2.21.0
Requires-Dist: marshmallow>=3.0.0
Requires-Dist: marshmallow_oneofschema>=2.0.1
Requires-Dist: backoff>=2.0.0
Requires-Dist: pydantic>=1.10.0
Requires-Dist: PyJWT>=2.8.0
Requires-Dist: packaging
Requires-Dist: ansys-hps-data-transfer-client>=0.3.0,<0.4.0
Requires-Dist: build==1.2.2.post1 ; extra == "build"
Requires-Dist: twine==6.1.0 ; extra == "build"
Requires-Dist: wheel ; extra == "build"
Requires-Dist: datamodel-code-generator==0.26.3 ; extra == "build"
Requires-Dist: ansys-sphinx-theme==1.5.3 ; extra == "doc"
Requires-Dist: autodoc_pydantic==2.1.0 ; extra == "doc"
Requires-Dist: jupyter_sphinx==0.5.3 ; extra == "doc"
Requires-Dist: nbsphinx==0.9.7 ; extra == "doc"
Requires-Dist: numpydoc==1.9.0 ; extra == "doc"
Requires-Dist: myst-parser==4.0.1 ; extra == "doc"
Requires-Dist: Sphinx==8.1.3 ; extra == "doc"
Requires-Dist: sphinx-autodoc-typehints==3.0.1 ; extra == "doc"
Requires-Dist: sphinxcontrib-globalsubs==0.1.2 ; extra == "doc"
Requires-Dist: sphinxcontrib-httpdomain==1.8.1 ; extra == "doc"
Requires-Dist: sphinx-copybutton==0.5.2 ; extra == "doc"
Requires-Dist: sphinx_design==0.6.1 ; extra == "doc"
Requires-Dist: sphinx-jinja==2.0.2 ; extra == "doc"
Requires-Dist: sphinxnotes-strike==1.2.1 ; extra == "doc"
Requires-Dist: sphinx-tabs==3.4.7 ; extra == "doc"
Requires-Dist: pytest==8.4.1 ; extra == "tests"
Requires-Dist: coverage==7.10.3 ; extra == "tests"
Requires-Dist: python-keycloak>=3.9.1,<4.0.0 ; extra == "tests"
Project-URL: Documentation, https://hps.docs.pyansys.com
Project-URL: Homepage, https://github.com/ansys/pyhps
Project-URL: Source, https://github.com/ansys/pyhps
Project-URL: Tracker, https://github.com/ansys/pyhps/issues
Provides-Extra: build
Provides-Extra: doc
Provides-Extra: tests
